{"fetched_at":1776073054382,"posts":[{"title":"Yaochen (feat. Kun of WayV) - OUTTA MY WAY","url":"https://www.reddit.com/r/popheads/comments/1sk0x6m/yaochen_feat_kun_of_wayv_outta_my_way/","created_utc":1776055643,"thumbnail":"","category":"mv"},{"title":"NCT WISH - Sticky","url":"https://www.reddit.com/r/popheads/comments/1sjmd0p/nct_wish_sticky/","created_utc":1776018477,"thumbnail":"","category":"mv"},{"title":"Labrinth - SHUT YOUR DAMN 95.7892","url":"https://www.reddit.com/r/popheads/comments/1sjwmc4/labrinth_shut_your_damn_957892/","created_utc":1776043244,"thumbnail":"","category":"song"}]}